[{
	"Nun": "1",
	"Bukrs": "0001",
	"Butxt": "АО РНПК",
	"Beber": "0001",
	"Bebtxt": "Цех № 1",
	"Year": "2018",
	"Month": "Январь",
	"Type": "0001",
	"TypeTxt": "Собственные работы",
	"Plan": 23423000,
	"Fact": 22434400
}, {
	"Nun": "2",
	"Bukrs": "0001",
	"Butxt": "АО РНПК",
	"Beber": "0001",
	"Bebtxt": "Цех № 1",
	"Year": "2018",
	"Month": "Январь",
	"Type": "0002",
	"TypeTxt": "Услуги подрядчика",
	"Plan": 13000344,
	"Fact": 12234500
}, {
	"Nun": "3",
	"Bukrs": "0001",
	"TypeTxt": "Материалы",
	"Type": "0003",
	"Plan": 4233000,
	"Fact": 2334500,
	"Month": "Январь",
	"Year": "2018",
	"Bebtxt": "Цех № 1",
	"Beber": "0001",
	"Butxt": "АО РНПК"
}]